Products.GenericSetup-5.0.0-py3.12-nspkg.pth
Products/GenericSetup/README.txt
Products/GenericSetup/__init__.py
Products/GenericSetup/components.py
Products/GenericSetup/configure.zcml
Products/GenericSetup/content.py
Products/GenericSetup/context.py
Products/GenericSetup/differ.py
Products/GenericSetup/events.py
Products/GenericSetup/exceptions.py
Products/GenericSetup/interfaces.py
Products/GenericSetup/meta.zcml
Products/GenericSetup/metadata.py
Products/GenericSetup/permissions.py
Products/GenericSetup/registry.py
Products/GenericSetup/rolemap.py
Products/GenericSetup/testing.py
Products/GenericSetup/tool.py
Products/GenericSetup/upgrade.py
Products/GenericSetup/utils.py
Products/GenericSetup/zcml.py
Products/GenericSetup/OFSP/__init__.py
Products/GenericSetup/OFSP/configure.zcml
Products/GenericSetup/OFSP/exportimport.py
Products/GenericSetup/OFSP/tests/__init__.py
Products/GenericSetup/OFSP/tests/test_exportimport.py
Products/GenericSetup/PageTemplates/__init__.py
Products/GenericSetup/PageTemplates/configure.zcml
Products/GenericSetup/PageTemplates/exportimport.py
Products/GenericSetup/PageTemplates/interfaces.py
Products/GenericSetup/PageTemplates/tests/__init__.py
Products/GenericSetup/PageTemplates/tests/test_exportimport.py
Products/GenericSetup/PluginIndexes/__init__.py
Products/GenericSetup/PluginIndexes/configure.zcml
Products/GenericSetup/PluginIndexes/exportimport.py
Products/GenericSetup/PluginIndexes/tests/__init__.py
Products/GenericSetup/PluginIndexes/tests/test_exportimport.py
Products/GenericSetup/PythonScripts/__init__.py
Products/GenericSetup/PythonScripts/configure.zcml
Products/GenericSetup/PythonScripts/exportimport.py
Products/GenericSetup/PythonScripts/interfaces.py
Products/GenericSetup/PythonScripts/tests/__init__.py
Products/GenericSetup/PythonScripts/tests/test_exportimport.py
Products/GenericSetup/ZCTextIndex/__init__.py
Products/GenericSetup/ZCTextIndex/configure.zcml
Products/GenericSetup/ZCTextIndex/exportimport.py
Products.GenericSetup-5.0.0.dist-info/LICENSE.txt
Products.GenericSetup-5.0.0.dist-info/METADATA
Products.GenericSetup-5.0.0.dist-info/WHEEL
Products.GenericSetup-5.0.0.dist-info/entry_points.txt
Products.GenericSetup-5.0.0.dist-info/namespace_packages.txt
Products.GenericSetup-5.0.0.dist-info/top_level.txt
Products.GenericSetup-5.0.0.dist-info/RECORD
