Metadata-Version: 2.1
Name: Products.GenericSetup
Version: 5.0.0
Summary: Read Zope configuration state from profile dirs / tarballs
Home-page: https://github.com/zopefoundation/Products.GenericSetup
Author: Zope Foundation and Contributors
Author-email: zope-dev@zope.dev
License: ZPL-2.1
Project-URL: Documentation, https://productsgenericsetup.readthedocs.io
Project-URL: Source code, https://github.com/zopefoundation/Products.GenericSetup
Project-URL: Issue tracker, https://github.com/zopefoundation/Products.GenericSetup/issues
Keywords: web application server zope zope4 cmf
Classifier: Development Status :: 5 - Production/Stable
Classifier: Framework :: Plone :: 5.2
Classifier: Framework :: Plone :: 6.0
Classifier: Framework :: Zope :: 5
Classifier: Intended Audience :: Developers
Classifier: License :: OSI Approved :: Zope Public License
Classifier: Programming Language :: Python
Classifier: Programming Language :: Python :: 3.9
Classifier: Programming Language :: Python :: 3.10
Classifier: Programming Language :: Python :: 3.11
Classifier: Programming Language :: Python :: 3.12
Classifier: Programming Language :: Python :: 3.13
Classifier: Programming Language :: Python :: Implementation :: CPython
Classifier: Topic :: Software Development
Classifier: Topic :: System :: Archiving :: Packaging
Classifier: Topic :: System :: Installation/Setup
Requires-Python: >=3.9
License-File: LICENSE.txt
Requires-Dist: packaging
Requires-Dist: setuptools
Requires-Dist: Zope>=4.0b4
Requires-Dist: five.localsitemanager
Requires-Dist: Products.PythonScripts
Requires-Dist: Products.ZCatalog
Provides-Extra: docs
Requires-Dist: Sphinx; extra == "docs"
Requires-Dist: repoze.sphinx.autointerface; extra == "docs"
